PythonbasicsZhongwenXilieJiaocheng/README.md
PythonbasicsZhongwenXilieJiaocheng/__init__.py
PythonbasicsZhongwenXilieJiaocheng/__main__.py
PythonbasicsZhongwenXilieJiaocheng/file.epub
PythonbasicsZhongwenXilieJiaocheng/index.html
PythonbasicsZhongwenXilieJiaocheng/css/__init__.py
PythonbasicsZhongwenXilieJiaocheng/css/annotations.css
PythonbasicsZhongwenXilieJiaocheng/css/main.css
PythonbasicsZhongwenXilieJiaocheng/css/normalize.css
PythonbasicsZhongwenXilieJiaocheng/css/popup.css
PythonbasicsZhongwenXilieJiaocheng/font/__init__.py
PythonbasicsZhongwenXilieJiaocheng/font/fontello.eot
PythonbasicsZhongwenXilieJiaocheng/font/fontello.svg
PythonbasicsZhongwenXilieJiaocheng/font/fontello.ttf
PythonbasicsZhongwenXilieJiaocheng/font/fontello.woff
PythonbasicsZhongwenXilieJiaocheng/img/__init__.py
PythonbasicsZhongwenXilieJiaocheng/img/annotator-glyph-sprite.png
PythonbasicsZhongwenXilieJiaocheng/img/annotator-icon-sprite.png
PythonbasicsZhongwenXilieJiaocheng/img/apple-touch-icon.png
PythonbasicsZhongwenXilieJiaocheng/img/cancelfullscreen.png
PythonbasicsZhongwenXilieJiaocheng/img/close.png
PythonbasicsZhongwenXilieJiaocheng/img/fullscreen.png
PythonbasicsZhongwenXilieJiaocheng/img/loader.gif
PythonbasicsZhongwenXilieJiaocheng/img/menu-icon.png
PythonbasicsZhongwenXilieJiaocheng/img/save.png
PythonbasicsZhongwenXilieJiaocheng/img/saved.png
PythonbasicsZhongwenXilieJiaocheng/img/settings-s.png
PythonbasicsZhongwenXilieJiaocheng/img/settings.png
PythonbasicsZhongwenXilieJiaocheng/img/star.png
PythonbasicsZhongwenXilieJiaocheng/js/__init__.py
PythonbasicsZhongwenXilieJiaocheng/js/epub.js
PythonbasicsZhongwenXilieJiaocheng/js/epub.min.js
PythonbasicsZhongwenXilieJiaocheng/js/epub.min.map
PythonbasicsZhongwenXilieJiaocheng/js/hooks.min.js
PythonbasicsZhongwenXilieJiaocheng/js/hooks.min.map
PythonbasicsZhongwenXilieJiaocheng/js/reader.js
PythonbasicsZhongwenXilieJiaocheng/js/reader.js.map
PythonbasicsZhongwenXilieJiaocheng/js/reader.min.js
pythonbasics_zhongwen_xilie_jiaocheng-2024.3.5.0.dist-info/METADATA
pythonbasics_zhongwen_xilie_jiaocheng-2024.3.5.0.dist-info/WHEEL
pythonbasics_zhongwen_xilie_jiaocheng-2024.3.5.0.dist-info/entry_points.txt
pythonbasics_zhongwen_xilie_jiaocheng-2024.3.5.0.dist-info/top_level.txt
pythonbasics_zhongwen_xilie_jiaocheng-2024.3.5.0.dist-info/RECORD
